{
	"version": "1.0.0",
	"date": "2025-05-30",
	"quality": "dev",
	"commit": "1234567890",
	"nameShort": "RedBox",
	"nameLong": "RedBox",
	"applicationName": "redbox",
	"dataFolderName": ".redbox",
	"win32MutexName": "redbox",
	"licenseName": "MIT",
	"serverGreeting": [],
	"serverLicense": [],
	"serverLicensePrompt": "",
	"serverApplicationName": "redbox-server-oss",
	"serverDataFolderName": ".redbox-server-oss",
	"tunnelApplicationName": "redbox-tunnel-oss",
	"win32DirName": "RedBox",
	"win32NameVersion": "RedBox",
	"win32RegValueName": "RedBox"
}
